{
  "$schema": "https://mintlify.com/docs.json",
  "theme": "mint",
  "name": "Happ",
  "colors": {
    "primary": "#00b894"
  },
  "navigation": {
    "languages": [
      {
  "language": "en",
  "pages": [
    "en/index",
    "en/privacy-policy",
    "en/terms-of-use",

    {
      "group": "FAQ",
      "pages": [
        "en/faq/how-to-buy-or-get-a-server",
        "en/faq/adding-configuration-subscription",
        "en/faq/share-configuration",
        "en/faq/local-network-connections",
        "en/faq/android-tv",
        "en/faq/apple-tv-tvos",
        "en/faq/ping",
        "en/faq/errors/index",
        "en/faq/errors/windows-update"
      ]
    },

    {
      "group": "Developer Documentation",
      "pages": [
        "en/dev-docs/crypto-link",
        "en/dev-docs/limited-links",
        "en/dev-docs/hwid-links",
        "en/dev-docs/app-management",
        "en/dev-docs/provider-id",
        "en/dev-docs/routing",
        "en/dev-docs/displaying-flags-and-smileys",
        "en/dev-docs/examples-of-links-and-parameters",
        "en/dev-docs/ping",
        "en/dev-docs/android-tv-api"
      ]
    },

    "en/contacts"
  ]
}
      ,
      {
        "language": "ru",
        "default": true,
        "pages": [
          "ru/index",
          "ru/privacy-policy",
          "ru/terms-of-use",

          {
            "group": "FAQ",
            "pages": [
              "ru/faq/how-to-buy-or-get-a-server",
              "ru/faq/adding-configuration-subscription",
              "ru/faq/share-configuration",
              "ru/faq/local-network-connections",
              "ru/faq/android-tv",
              "ru/faq/apple-tv-tvos",
              "ru/faq/ping",
              "ru/faq/errors",
              "ru/faq/errors/windows-update"
            ]
          },

          {
  "group": "Техническая документация",
  "pages": [
    "ru/technical-docs/encrypted-link",
    "ru/technical-docs/limited-links",
    "ru/technical-docs/hwid-links",
    "ru/technical-docs/app-management",
    "ru/technical-docs/provider-id",
    "ru/technical-docs/routing",
    "ru/technical-docs/emoji",
    "ru/technical-docs/examples-of-links-and-parameters",
    "ru/technical-docs/android-tv-api"
  ]
}
,

          "ru/contacts"
        ]
      },
           {
        "language": "zh",
        "pages": [
          "zh/index",
          "zh/privacy-policy",
          "zh/terms-of-use",

          {
            "group": "FAQ",
            "pages": [
              "zh/faq/how-to-buy-or-get-a-server",
              "zh/faq/adding-configuration-subscription",
              "zh/faq/share-configuration",
              "zh/faq/local-network-connections",
              "zh/faq/android-tv",
              "zh/faq/apple-tv-tvos",
              "zh/faq/ping",
              "zh/faq/errors/index",
              "zh/faq/errors/windows-update"
            ]
          },

          {
            "group": "开发者文档",
            "pages": [
              "zh/dev-docs/crypto-link",
              "zh/dev-docs/app-management",
              "zh/dev-docs/provider-id",
              "zh/dev-docs/routing",
              "zh/dev-docs/displaying-flags-and-smileys",
              "zh/dev-docs/examples-of-links-and-parameters",
              "zh/dev-docs/hwid-links",
              "zh/dev-docs/limited-links",
              "zh/dev-docs/ping",
              "zh/dev-docs/android-tv-api"
            ]
          },

          "zh/contacts"
        ]
      }

    ]
  }
}
